cup/__init__.py
cup/cache.py
cup/const.py
cup/decorators.py
cup/err.py
cup/exfile.py
cup/flag.py
cup/log.py
cup/mail.py
cup/net/__init__.py
cup/net/asyn/__init__.py
cup/net/asyn/common.py
cup/net/asyn/conn.py
cup/net/asyn/context.py
cup/net/asyn/ioloop.py
cup/net/asyn/msg.py
cup/net/asyn/msgcenter.py
cup/net/ipaddr.py
cup/net/route.py
cup/platforms.py
cup/res/__init__.py
cup/res/linux.py
cup/res/mac.py
cup/services/__init__.py
cup/services/autowait.py
cup/services/buffers.py
cup/services/executor.py
cup/services/generator.py
cup/services/heartbeat.py
cup/services/msgbroker.py
cup/services/serializer.py
cup/services/threadpool.py
cup/shell/__init__.py
cup/shell/expect.py
cup/shell/oper.py
cup/storage/__init__.py
cup/storage/obj.py
cup/thread.py
cup/timeplus.py
cup/unittest.py
cup/update_open_source.sh
cup/util/__init__.py
cup/util/conf.py
cup/util/constants.py
cup/util/context.py
cup/util/misc.py
cup/util/typechecker.py
cup/version.py
cup/web/__init__.py
cup-3.2.35.dist-info/METADATA
cup-3.2.35.dist-info/WHEEL
cup-3.2.35.dist-info/licenses/LICENSE
cup-3.2.35.dist-info/RECORD
