Metadata-Version: 2.4
Name: cup
Version: 3.2.35
Summary: A common useful python library
License: Apache License V2
License-File: LICENSE
Keywords: pylib,lib,common,cup
Author: CUP Dev Team lead by Guannan Ma
Author-email: mythmgn@hotmail.com
Maintainer: Guannan Ma
Maintainer-email: mythmgn@hotmail.com
Requires-Python: >=3.9,<3.14
Classifier: Development Status :: 5 - Production/Stable
Classifier: Intended Audience :: Developers
Classifier: License :: Other/Proprietary License
Classifier: Programming Language :: Python :: 3
Classifier: Programming Language :: Python :: 3.9
Classifier: Programming Language :: Python :: 3.10
Classifier: Programming Language :: Python :: 3.11
Classifier: Programming Language :: Python :: 3.12
Classifier: Programming Language :: Python :: 3.13
Classifier: Topic :: Software Development :: Libraries :: Python Modules
Requires-Dist: cffi (>1.15.1)
Requires-Dist: netifaces (>=0.11.0,<0.12.0)
Requires-Dist: pexpect (>=4.8.0,<5.0.0)
Requires-Dist: psutil (>=5.9.4,<6.0.0)
Requires-Dist: pyproject-toml (>=0.1.0,<0.2.0)
Requires-Dist: pytest (>=8.3.5,<9.0.0)
Requires-Dist: pytz (>=2025.2,<2026.0)
Requires-Dist: requests (>=2.28.2,<3.0.0)
Requires-Dist: twist (>=0.0.1,<0.0.2)
Project-URL: Homepage, https://github.com/baidu/CUP
